pulumi_kestra/__init__.py
pulumi_kestra/_inputs.py
pulumi_kestra/_utilities.py
pulumi_kestra/app.py
pulumi_kestra/binding.py
pulumi_kestra/dashboard.py
pulumi_kestra/flow.py
pulumi_kestra/get_binding.py
pulumi_kestra/get_flow.py
pulumi_kestra/get_group.py
pulumi_kestra/get_kv.py
pulumi_kestra/get_namespace.py
pulumi_kestra/get_namespace_file.py
pulumi_kestra/get_role.py
pulumi_kestra/get_service_account.py
pulumi_kestra/get_service_account_api_tokens.py
pulumi_kestra/get_template.py
pulumi_kestra/get_tenant.py
pulumi_kestra/get_test.py
pulumi_kestra/get_user.py
pulumi_kestra/get_user_api_tokens.py
pulumi_kestra/get_worker_group.py
pulumi_kestra/group.py
pulumi_kestra/kv.py
pulumi_kestra/namespace.py
pulumi_kestra/namespace_file.py
pulumi_kestra/namespace_secret.py
pulumi_kestra/outputs.py
pulumi_kestra/provider.py
pulumi_kestra/pulumi-plugin.json
pulumi_kestra/py.typed
pulumi_kestra/role.py
pulumi_kestra/security_integration.py
pulumi_kestra/service_account.py
pulumi_kestra/service_account_api_token.py
pulumi_kestra/template.py
pulumi_kestra/tenant.py
pulumi_kestra/test.py
pulumi_kestra/user.py
pulumi_kestra/user_api_token.py
pulumi_kestra/user_password.py
pulumi_kestra/worker_group.py
pulumi_kestra/config/__init__.py
pulumi_kestra/config/__init__.pyi
pulumi_kestra/config/vars.py
pulumi_kestra-1.0.0.dist-info/METADATA
pulumi_kestra-1.0.0.dist-info/WHEEL
pulumi_kestra-1.0.0.dist-info/top_level.txt
pulumi_kestra-1.0.0.dist-info/RECORD
